sqlalchemy_mock/__init__.py
sqlalchemy_mock/async_session.py
sqlalchemy_mock/execute.py
sqlalchemy_mock/query.py
sqlalchemy_mock/session.py
sqlalchemy_mock/utils.py
sqlalchemy_mock-1.1.0.dist-info/METADATA
sqlalchemy_mock-1.1.0.dist-info/WHEEL
sqlalchemy_mock-1.1.0.dist-info/RECORD
