Metadata-Version: 2.1
Name: sqlalchemy-mock
Version: 1.1.0
Summary: The package for working with SQLAlchemy in unit tests
Author: ivanostapiuk
Author-email: ost.ivan13@gmail.com
Requires-Python: >=3.0,<4.0
Classifier: Programming Language :: Python :: 3
Classifier: Programming Language :: Python :: 3.4
Classifier: Programming Language :: Python :: 3.5
Classifier: Programming Language :: Python :: 3.6
Classifier: Programming Language :: Python :: 3.7
Classifier: Programming Language :: Python :: 3.8
Classifier: Programming Language :: Python :: 3.9
Classifier: Programming Language :: Python :: 3.10
Classifier: Programming Language :: Python :: 3.11
